gx_tool_db/__init__.py
gx_tool_db/config.py
gx_tool_db/credentials.json
gx_tool_db/db.py
gx_tool_db/io.py
gx_tool_db/main.py
gx_tool_db/models.py
gx_tool_db/results.py
gx_tool_db/sheets.py
gx_tool_db/workflows.py
gx_tool_db-0.4.0.dist-info/LICENSE
gx_tool_db-0.4.0.dist-info/METADATA
gx_tool_db-0.4.0.dist-info/WHEEL
gx_tool_db-0.4.0.dist-info/entry_points.txt
gx_tool_db-0.4.0.dist-info/top_level.txt
gx_tool_db-0.4.0.dist-info/RECORD
