Metadata-Version: 2.1
Name: gx-tool-db
Version: 0.4.0
Summary: Management utility for YAML database of Galaxy tools
Home-page: https://github.com/galaxyproject/gx-tool-db
Author: Galaxy Project and Community
Author-email: jmchilton@gmail.com
License: MIT
Keywords: galaxy
Platform: UNKNOWN
Classifier: Development Status :: 5 - Production/Stable
Classifier: Intended Audience :: Developers
Classifier: Environment :: Console
Classifier: License :: OSI Approved :: MIT License
Classifier: Operating System :: POSIX
Classifier: Topic :: Software Development
Classifier: Topic :: Software Development :: Code Generators
Classifier: Topic :: Software Development :: Testing
Classifier: Natural Language :: English
Classifier: Programming Language :: Python :: 3
Classifier: Programming Language :: Python :: 3.6
Classifier: Programming Language :: Python :: 3.7
Classifier: Programming Language :: Python :: 3.8
Classifier: Programming Language :: Python :: 3.9
License-File: LICENSE
Requires-Dist: google-api-python-client
Requires-Dist: google-auth-httplib2
Requires-Dist: google-auth-oauthlib
Requires-Dist: gspread
Requires-Dist: gxformat2
Requires-Dist: packaging
Requires-Dist: pydantic
Requires-Dist: requests
Requires-Dist: pyyaml
Requires-Dist: typing-extensions
Requires-Dist: urllib3
